autofaiss/__init__.py
autofaiss/version.py
autofaiss/external/__init__.py
autofaiss/external/build.py
autofaiss/external/descriptions.py
autofaiss/external/metadata.py
autofaiss/external/optimize.py
autofaiss/external/quantize.py
autofaiss/external/scores.py
autofaiss/indices/__init__.py
autofaiss/indices/build.py
autofaiss/indices/distributed.py
autofaiss/indices/faiss_index_wrapper.py
autofaiss/indices/index_factory.py
autofaiss/indices/index_utils.py
autofaiss/indices/memory_efficient_flat_index.py
autofaiss/indices/search.py
autofaiss/indices/training.py
autofaiss/metrics/__init__.py
autofaiss/metrics/benchmark.py
autofaiss/metrics/recalls.py
autofaiss/metrics/reconstruction.py
autofaiss/utils/__init__.py
autofaiss/utils/algorithms.py
autofaiss/utils/array_functions.py
autofaiss/utils/cast.py
autofaiss/utils/decorators.py
autofaiss/utils/path.py
autofaiss_community-2.17.0.data/data/README.md
autofaiss_community-2.17.0.data/data/requirements.txt
autofaiss_community-2.17.0.dist-info/licenses/LICENSE
tests/__init__.py
tests/unit/__init__.py
tests/unit/test_build.py
tests/unit/test_distributed.py
tests/unit/test_mem_efficient_flat_index.py
tests/unit/test_np_quantize.py
tests/unit/test_optimize.py
tests/unit/test_quantize.py
tests/unit/test_scoring_tuning.py
tests/unit/test_utils.py
tests/unit/test_version.py
autofaiss_community-2.17.0.dist-info/METADATA
autofaiss_community-2.17.0.dist-info/WHEEL
autofaiss_community-2.17.0.dist-info/entry_points.txt
autofaiss_community-2.17.0.dist-info/top_level.txt
autofaiss_community-2.17.0.dist-info/RECORD
