Metadata-Version: 2.4
Name: autofaiss-community
Version: 2.17.0
Summary: # AutoFaiss Community
Home-page: https://github.com/satishlokkoju/autofaiss
Author: Criteo
Classifier: License :: OSI Approved :: Apache Software License
Classifier: Operating System :: OS Independent
Classifier: Programming Language :: Python :: 3
Classifier: Programming Language :: Python :: 3.10
Classifier: Programming Language :: Python :: 3.11
Classifier: Programming Language :: Python :: 3.12
Classifier: Intended Audience :: Developers
Requires-Python: >=3.10
License-File: LICENSE
Requires-Dist: fire<0.7.0,>=0.4.0
Requires-Dist: numpy<2,>=1.19.5
Requires-Dist: pandas<3,>=1.1.5
Requires-Dist: pyarrow<30,>=6.0.1
Requires-Dist: tqdm<5,>=4.62.3
Requires-Dist: faiss-cpu<2,>=1
Requires-Dist: fsspec>=2022.1.0
Requires-Dist: embedding_reader<2,>=1.8.0
Dynamic: author
Dynamic: classifier
Dynamic: description
Dynamic: description-content-type
Dynamic: home-page
Dynamic: license-file
Dynamic: requires-dist
Dynamic: requires-python
Dynamic: summary
